MANIFEST.in
README.rst
setup.py
lib/world/cheaptrick.cpp
lib/world/cheaptrick.h
lib/world/common.cpp
lib/world/common.h
lib/world/constantnumbers.h
lib/world/copying.txt
lib/world/d4c.cpp
lib/world/d4c.h
lib/world/dio.cpp
lib/world/dio.h
lib/world/fft.cpp
lib/world/fft.h
lib/world/matlabfunctions.cpp
lib/world/matlabfunctions.h
lib/world/stonemask.cpp
lib/world/stonemask.h
lib/world/synthesis.cpp
lib/world/synthesis.h
pysas/__init__.py
pysas/decorators.py
pysas/excite.pyx
pysas/mcep.pyx
pysas/pyexcite.py
pysas/utils.py
pysas/world.pyx
pysas/libworld/__init__.pxd
pysas/libworld/__init__.py
pysas/libworld/cheaptrick.pxd
pysas/libworld/d4c.pxd
pysas/libworld/dio.pxd
pysas/libworld/matlabfunctions.pxd
pysas/libworld/stonemask.pxd
pysas/libworld/synthesis.pxd
pysas/synthesis/__init__.py
pysas/synthesis/cysynthesis.pyx
pysas/synthesis/mlsa.pyx
pysas/synthesis/pymlsa.py
pysas/synthesis/synthesis.py
test/test_filter.py
test/test_mcep.py
test/test_world.py
test/cmu_arctic/COPYING.txt
test/cmu_arctic/arctic_a0001.wav
test/cmu_arctic/source.wav