Metadata-Version: 1.1
Name: pysas
Version: 0.02
Summary: Speech Analysis and Synthesis for Python
Home-page: https://github.com/shunsukeaihara/pysas
Author: Shunsuke Aihara
Author-email: aihara@argmax.jp
License: MIT License
Platform: UNKNOWN
Classifier: Programming Language :: Python
Classifier: Programming Language :: Python :: 3
Classifier: Programming Language :: Python :: 2
Classifier: Intended Audience :: Science/Research
Classifier: Programming Language :: Python
Classifier: Topic :: Scientific/Engineering
